batch_requests/__init__.py
batch_requests/exceptions.py
batch_requests/settings.py
batch_requests/utils.py
batch_requests/views.py
batch_requests/concurrent/__init__.py
batch_requests/concurrent/executor.py
batch_requests/migrations/__init__.py
djago_batch_requests-0.1.1.dist-info/DESCRIPTION.rst
djago_batch_requests-0.1.1.dist-info/METADATA
djago_batch_requests-0.1.1.dist-info/RECORD
djago_batch_requests-0.1.1.dist-info/WHEEL
djago_batch_requests-0.1.1.dist-info/metadata.json
djago_batch_requests-0.1.1.dist-info/top_level.txt
